nanopy_faucet/__init__.py
nanopy_faucet/__main__.py
nanopy_faucet/main.py
nanopy_faucet/static/index.html
nanopy_faucet-2.0.5.dist-info/METADATA
nanopy_faucet-2.0.5.dist-info/WHEEL
nanopy_faucet-2.0.5.dist-info/entry_points.txt
nanopy_faucet-2.0.5.dist-info/top_level.txt
nanopy_faucet-2.0.5.dist-info/RECORD
