Metadata-Version: 2.4
Name: nanopy-faucet
Version: 2.0.5
Summary: Testnet faucet for NanoPy Network
Home-page: https://github.com/Web3-League/faucet-testnet
Author: NanoPy Team
Author-email: dev@nanopy.chain
Keywords: blockchain faucet nanopy testnet
Classifier: Development Status :: 4 - Beta
Classifier: Intended Audience :: Developers
Classifier: License :: OSI Approved :: MIT License
Classifier: Programming Language :: Python :: 3
Classifier: Programming Language :: Python :: 3.10
Classifier: Programming Language :: Python :: 3.11
Classifier: Programming Language :: Python :: 3.12
Requires-Python: >=3.8
Requires-Dist: aiohttp>=3.8.0
Requires-Dist: click>=8.0.0
Requires-Dist: rich>=12.0.0
Requires-Dist: eth-account>=0.8.0
Requires-Dist: eth-utils>=2.0.0
Dynamic: author
Dynamic: author-email
Dynamic: classifier
Dynamic: description
Dynamic: description-content-type
Dynamic: home-page
Dynamic: keywords
Dynamic: requires-dist
Dynamic: requires-python
Dynamic: summary
